odoo/addons/account_move_line_reconcile_manual/README.rst
odoo/addons/account_move_line_reconcile_manual/__init__.py
odoo/addons/account_move_line_reconcile_manual/__manifest__.py
odoo/addons/account_move_line_reconcile_manual/i18n/account_move_line_reconcile_manual.pot
odoo/addons/account_move_line_reconcile_manual/i18n/es.po
odoo/addons/account_move_line_reconcile_manual/i18n/fr.po
odoo/addons/account_move_line_reconcile_manual/i18n/hr.po
odoo/addons/account_move_line_reconcile_manual/i18n/it.po
odoo/addons/account_move_line_reconcile_manual/i18n/pt.po
odoo/addons/account_move_line_reconcile_manual/i18n/pt_BR.po
odoo/addons/account_move_line_reconcile_manual/i18n/sv.po
odoo/addons/account_move_line_reconcile_manual/models/__init__.py
odoo/addons/account_move_line_reconcile_manual/models/account_reconcile_manual_model.py
odoo/addons/account_move_line_reconcile_manual/readme/CONTRIBUTORS.rst
odoo/addons/account_move_line_reconcile_manual/readme/DESCRIPTION.rst
odoo/addons/account_move_line_reconcile_manual/security/ir.model.access.csv
odoo/addons/account_move_line_reconcile_manual/static/description/icon.png
odoo/addons/account_move_line_reconcile_manual/static/description/index.html
odoo/addons/account_move_line_reconcile_manual/static/description/sshot_full_rec.png
odoo/addons/account_move_line_reconcile_manual/static/description/sshot_partial_rec.png
odoo/addons/account_move_line_reconcile_manual/static/description/sshot_rec_writeoff.png
odoo/addons/account_move_line_reconcile_manual/tests/__init__.py
odoo/addons/account_move_line_reconcile_manual/tests/test_reconcile_manual.py
odoo/addons/account_move_line_reconcile_manual/views/account_move_line.xml
odoo/addons/account_move_line_reconcile_manual/views/account_reconcile_manual_model.xml
odoo/addons/account_move_line_reconcile_manual/wizards/__init__.py
odoo/addons/account_move_line_reconcile_manual/wizards/account_move_line_reconcile_manual.py
odoo_addon_account_move_line_reconcile_manual-16.0.2.0.0.12.dist-info/METADATA
odoo_addon_account_move_line_reconcile_manual-16.0.2.0.0.12.dist-info/WHEEL
odoo_addon_account_move_line_reconcile_manual-16.0.2.0.0.12.dist-info/top_level.txt
odoo_addon_account_move_line_reconcile_manual-16.0.2.0.0.12.dist-info/RECORD
